{
    "cooldown": 80,
    "onEveryCheckpoint":false,
    "freeUseCount":3,
    "freeTeleportCooldown":3,
    "enableAdsOnSecondLevels":true,
    "nextCheckpointPrice" : 3,
    "world1text" : "Thanks for playing !!!\nWait for the new updates ! \nPurchase MARS for new experience!",
    "world2text" : "Thanks for support !!!\nWait for the new updates ! \nOur Jump Up Team",
    "removeAdsPopupFrequency" : 4,
    "enableInterstitial" : true,
    "canOpenLevelAfterFinish" : false,
    "saveOnFall" : false,
    "sendData": false,
    "showAdOnLevelStart" : true,
    "noobsCount" : 6,
    "proCount" : 6,
    "serverAddress" : "http://217.25.92.79:5000/",
    "showData" : false
}
